LICENCE
MANIFEST.in
README.md
setup.py
nlpbox/__init__.py
nlpbox/charnum.py
nlpbox/clean.py
nlpbox/thesaurus.py
nlpbox.egg-info/PKG-INFO
nlpbox.egg-info/SOURCES.txt
nlpbox.egg-info/dependency_links.txt
nlpbox.egg-info/not-zip-safe
nlpbox.egg-info/requires.txt
nlpbox.egg-info/top_level.txt