Metadata-Version: 1.1
Name: nlpbox
Version: 1.1.2
Summary: a nlpbox toolbox
Home-page: https://github.com/hycis/NLPBox
Author: Wu Zhen Zhou
Author-email: hyciswu@gmail.com
License: Apache 2.0, see LICENCE
Download-URL: https://github.com/hycis/NLPBox/tarball/1.1.2
Platform: UNKNOWN
